satis/Uref_Probes.dat
satis/__init__.py
satis/avbp2global.py
satis/avbp2global_compute_ftf.py
satis/avbp2global_diagnostics.py
satis/avbp2global_read_inputs.py
satis/cerfacs_plot.py
satis/cli.py
satis/io.py
satis/newCerfacs.png
satis/satis_library.py
satis/temporal_analysis_tool.py
satis/__pycache__/__init__.cpython-37.pyc
satis/__pycache__/__init__.cpython-39.pyc
satis/__pycache__/avbp2global.cpython-37.pyc
satis/__pycache__/avbp2global_compute_ftf.cpython-37.pyc
satis/__pycache__/avbp2global_diagnostics.cpython-37.pyc
satis/__pycache__/avbp2global_read_inputs.cpython-37.pyc
satis/__pycache__/cerfacs_plot.cpython-37.pyc
satis/__pycache__/cli.cpython-37.pyc
satis/__pycache__/satis.cpython-37.pyc
satis/__pycache__/satis_library.cpython-37.pyc
satis/__pycache__/spectral.cpython-37.pyc
satis/__pycache__/spectral_library.cpython-37.pyc
satis/__pycache__/temporal_analysis_tool.cpython-39.pyc
satis-0.0.5.dist-info/LICENSE
satis-0.0.5.dist-info/METADATA
satis-0.0.5.dist-info/WHEEL
satis-0.0.5.dist-info/entry_points.txt
satis-0.0.5.dist-info/top_level.txt
satis-0.0.5.dist-info/RECORD
