Metadata-Version: 2.1
Name: satis
Version: 0.0.5
Summary: Spectral Analysis for TIme Signals
Home-page: https://nitrox.cerfacs.fr/opentea/satis
Author: Antoine Dauptain, Franchine Ni, Tamon Nakano, Matthieu Rossi
Author-email: coop@cerfacs.fr
License: UNKNOWN
Keywords: spectral analysis,CFD,signal processing
Platform: UNKNOWN
